{
  "id": "24887bd32d83564ea780",
  "kind": "part",
  "bookId": "journeys-g3-book-1",
  "unitId": "unit-3-3e7eaa87",
  "lessonId": "lesson-2d6f0fe0",
  "partId": "part-ab394f3e",
  "partTitle": "Jump! from the Life of Michael Jordan",
  "partGoals": [
    "Jump!",
    "Introduce the Internet"
  ],
  "activityNotes": [
    "main selection: Jump!",
    "computers: Introduce the Internet"
  ],
  "languageFocus": {
    "grammarNotes": [],
    "writingNotes": []
  },
  "sourcePageRange": {
    "startPage": 366,
    "endPage": 366
  },
  "scanProfile": "balanced",
  "contextVersion": "v1",
  "createdAt": "2026-05-01T21:00:22.117Z",
  "updatedAt": "2026-05-01T21:00:22.117Z"
}