{
  "id": "681bca2cbd27a08ab0a0",
  "kind": "part",
  "bookId": "journeys-g3-book-1",
  "unitId": "unit-3-3e7eaa87",
  "lessonId": "lesson-a8d2adbd",
  "partId": "part-f05870eb",
  "partTitle": "Your Turn.",
  "partGoals": [
    "Basic Words: nurse, work, shirt, hurt, first, word, serve, curly, dirt, third, worry, turn, stir, firm"
  ],
  "activityNotes": [
    "spelling words: Basic Words: nurse, work, shirt, hurt, first, word, serve, curly, dirt, third, worry, turn, stir, firm"
  ],
  "languageFocus": {
    "grammarNotes": [],
    "writingNotes": []
  },
  "sourcePageRange": {
    "startPage": 509,
    "endPage": 509
  },
  "scanProfile": "balanced",
  "contextVersion": "v1",
  "createdAt": "2026-05-01T21:00:22.117Z",
  "updatedAt": "2026-05-01T21:00:22.117Z"
}