{
  "id": "a26f2f93d89ebf90f4f5",
  "kind": "part",
  "bookId": "journeys-g3-book-1",
  "unitId": "unit-2-269922a3",
  "lessonId": "lesson-de5fde9a",
  "partId": "part-d869a540",
  "partTitle": "Grammar/Write to Respond",
  "partGoals": [],
  "activityNotes": [
    "writing mode: Write to Respond: Compare/ Contrast Paragraph; Focus Trait: Organization: Topic Sentence"
  ],
  "languageFocus": {
    "grammarNotes": [],
    "writingNotes": [
      "Write to Respond: Compare/ Contrast Paragraph",
      "Focus Trait: Organization: Topic Sentence"
    ]
  },
  "sourcePageRange": {
    "startPage": 250,
    "endPage": 250
  },
  "scanProfile": "balanced",
  "contextVersion": "v1",
  "createdAt": "2026-05-01T21:00:22.117Z",
  "updatedAt": "2026-05-01T21:00:22.117Z"
}